setup.py
shinkenplugins/__init__.py
shinkenplugins.plugins.nova.egg-info/PKG-INFO
shinkenplugins.plugins.nova.egg-info/SOURCES.txt
shinkenplugins.plugins.nova.egg-info/dependency_links.txt
shinkenplugins.plugins.nova.egg-info/entry_points.txt
shinkenplugins.plugins.nova.egg-info/namespace_packages.txt
shinkenplugins.plugins.nova.egg-info/requires.txt
shinkenplugins.plugins.nova.egg-info/top_level.txt
shinkenplugins/plugins/__init__.py
shinkenplugins/plugins/nova/__init__.py
shinkenplugins/plugins/nova/nova.py