Metadata-Version: 1.0
Name: shinkenplugins.plugins.nova
Version: 1.0
Summary: A Shinken plugin to check the OpenStack Nova service
Home-page: https://github.com/savoirfairelinux/monitoring-tools
Author: Alexandre Viau
Author-email: alexandre.viau@savoirfairelinux.com
License: GPL3+
Platform: any
